dice_ml/__init__.py
dice_ml/constants.py
dice_ml/counterfactual_explanations.py
dice_ml/data.py
dice_ml/dice.py
dice_ml/diverse_counterfactuals.py
dice_ml/model.py
dice_ml/data_interfaces/__init__.py
dice_ml/data_interfaces/base_data_interface.py
dice_ml/data_interfaces/private_data_interface.py
dice_ml/data_interfaces/public_data_interface.py
dice_ml/explainer_interfaces/__init__.py
dice_ml/explainer_interfaces/dice_KD.py
dice_ml/explainer_interfaces/dice_genetic.py
dice_ml/explainer_interfaces/dice_pytorch.py
dice_ml/explainer_interfaces/dice_random.py
dice_ml/explainer_interfaces/dice_tensorflow1.py
dice_ml/explainer_interfaces/dice_tensorflow2.py
dice_ml/explainer_interfaces/explainer_base.py
dice_ml/explainer_interfaces/feasible_base_vae.py
dice_ml/explainer_interfaces/feasible_model_approx.py
dice_ml/model_interfaces/__init__.py
dice_ml/model_interfaces/base_model.py
dice_ml/model_interfaces/keras_tensorflow_model.py
dice_ml/model_interfaces/pytorch_model.py
dice_ml/schema/__init__.py
dice_ml/schema/counterfactual_explanations_v1.0.json
dice_ml/schema/counterfactual_explanations_v2.0.json
dice_ml/utils/__init__.py
dice_ml/utils/exception.py
dice_ml/utils/helpers.py
dice_ml/utils/neuralnetworks.py
dice_ml/utils/serialize.py
dice_ml/utils/sample_architecture/__init__.py
dice_ml/utils/sample_architecture/vae_model.py
dice_ml/utils/sample_trained_models/adult-margin-0.165-validity_reg-42.0-epoch-25-base-gen.pth
dice_ml/utils/sample_trained_models/adult-margin-0.344-validity_reg-76.0-epoch-25-ae-gen.pth
dice_ml/utils/sample_trained_models/adult.h5
dice_ml/utils/sample_trained_models/adult.pkl
dice_ml/utils/sample_trained_models/adult.pth
dice_ml/utils/sample_trained_models/adult_2nodes.pth
dice_ml/utils/sample_trained_models/custom.sav
dice_ml/utils/sample_trained_models/custom_binary.sav
dice_ml/utils/sample_trained_models/custom_multiclass.sav
dice_ml/utils/sample_trained_models/custom_regression.sav
dice_ml/utils/sample_trained_models/custom_vars.sav
dice_ml-0.11.dist-info/LICENSE
dice_ml-0.11.dist-info/METADATA
dice_ml-0.11.dist-info/WHEEL
dice_ml-0.11.dist-info/top_level.txt
dice_ml-0.11.dist-info/RECORD
