Metadata-Version: 2.1
Name: dice-ml
Version: 0.11
Summary: Generate Diverse Counterfactual Explanations for any machine learning model.
Home-page: https://github.com/interpretml/DiCE
Download-URL: https://github.com/interpretml/DiCE/archive/v0.11.tar.gz
Author: Ramaravind Mothilal, Amit Sharma, Chenhao Tan
Author-email: raam.arvind93@gmail.com
License: MIT
Keywords: machine-learning explanation interpretability counterfactual
Classifier: Intended Audience :: Developers
Classifier: Intended Audience :: Science/Research
Classifier: Programming Language :: Python :: 3
Classifier: Programming Language :: Python :: 3.7
Classifier: Programming Language :: Python :: 3.8
Classifier: Programming Language :: Python :: 3.9
Classifier: Programming Language :: Python :: 3.10
Classifier: Programming Language :: Python :: 3.11
Classifier: License :: OSI Approved :: MIT License
Classifier: Operating System :: OS Independent
Requires-Python: >=3.6
License-File: LICENSE
Requires-Dist: jsonschema
Requires-Dist: numpy
Requires-Dist: pandas<2.0.0
Requires-Dist: scikit-learn
Requires-Dist: tqdm
Requires-Dist: raiutils>=0.4.0
Provides-Extra: deeplearning
Requires-Dist: tensorflow>=1.13.1; extra == "deeplearning"
Requires-Dist: torch; extra == "deeplearning"
